digitalhub_ml/__init__.py
digitalhub_ml/entities/__init__.py
digitalhub_ml/entities/entity_types.py
digitalhub_ml/entities/registries.py
digitalhub_ml/entities/model/__init__.py
digitalhub_ml/entities/model/builder.py
digitalhub_ml/entities/model/crud.py
digitalhub_ml/entities/model/models.py
digitalhub_ml/entities/model/spec.py
digitalhub_ml/entities/model/status.py
digitalhub_ml/entities/model/entity/__init__.py
digitalhub_ml/entities/model/entity/_base.py
digitalhub_ml/entities/model/entity/huggingface.py
digitalhub_ml/entities/model/entity/mlflow.py
digitalhub_ml/entities/model/entity/model.py
digitalhub_ml/entities/model/entity/sklearn.py
digitalhub_ml/entities/project/__init__.py
digitalhub_ml/entities/project/builder.py
digitalhub_ml/entities/project/crud.py
digitalhub_ml/entities/project/spec.py
digitalhub_ml/entities/project/entity/__init__.py
digitalhub_ml/entities/project/entity/ml.py
digitalhub_ml/entities/run/__init__.py
digitalhub_ml/entities/run/models.py
digitalhub_ml/entities/run/spec.py
digitalhub_ml/entities/run/status.py
digitalhub_ml/entities/utils/__init__.py
digitalhub_ml/entities/utils/mlflow.py
digitalhub_ml-0.7.0.dist-info/METADATA
digitalhub_ml-0.7.0.dist-info/WHEEL
digitalhub_ml-0.7.0.dist-info/top_level.txt
digitalhub_ml-0.7.0.dist-info/RECORD
