Metadata-Version: 2.1
Name: digitalhub-ml
Version: 0.7.0
Summary: Python SDK for DHCore ml layer
Author-email: Fondazione Bruno Kessler <dslab@fbk.eu>, Matteo Martini <mmartini@fbk.eu>
Keywords: data,dataops,kubernetes
Classifier: License :: OSI Approved :: Apache Software License
Classifier: Programming Language :: Python :: 3.9
Classifier: Programming Language :: Python :: 3.10
Requires-Python: >=3.9
Requires-Dist: digitalhub-data<0.8,>=0.7.0b
Provides-Extra: mlflow
Requires-Dist: mlflow; extra == "mlflow"
